{ "frames": [
   {
    "filename": "golem1 0.aseprite",
    "frame": { "x": 0, "y": 0, "w": 100, "h": 100 },
    "rotated": false,
    "trimmed": false,
    "spriteSourceSize": { "x": 0, "y": 0, "w": 100, "h": 100 },
    "sourceSize": { "w": 100, "h": 100 },
    "duration": 100
   },
   {
    "filename": "golem1 1.aseprite",
    "frame": { "x": 100, "y": 0, "w": 100, "h": 100 },
    "rotated": false,
    "trimmed": false,
    "spriteSourceSize": { "x": 0, "y": 0, "w": 100, "h": 100 },
    "sourceSize": { "w": 100, "h": 100 },
    "duration": 100
   },
   {
    "filename": "golem1 2.aseprite",
    "frame": { "x": 200, "y": 0, "w": 100, "h": 100 },
    "rotated": false,
    "trimmed": false,
    "spriteSourceSize": { "x": 0, "y": 0, "w": 100, "h": 100 },
    "sourceSize": { "w": 100, "h": 100 },
    "duration": 100
   },
   {
    "filename": "golem1 3.aseprite",
    "frame": { "x": 300, "y": 0, "w": 100, "h": 100 },
    "rotated": false,
    "trimmed": false,
    "spriteSourceSize": { "x": 0, "y": 0, "w": 100, "h": 100 },
    "sourceSize": { "w": 100, "h": 100 },
    "duration": 100
   },
   {
    "filename": "golem1 4.aseprite",
    "frame": { "x": 0, "y": 100, "w": 100, "h": 100 },
    "rotated": false,
    "trimmed": false,
    "spriteSourceSize": { "x": 0, "y": 0, "w": 100, "h": 100 },
    "sourceSize": { "w": 100, "h": 100 },
    "duration": 100
   },
   {
    "filename": "golem1 5.aseprite",
    "frame": { "x": 0, "y": 0, "w": 100, "h": 100 },
    "rotated": false,
    "trimmed": false,
    "spriteSourceSize": { "x": 0, "y": 0, "w": 100, "h": 100 },
    "sourceSize": { "w": 100, "h": 100 },
    "duration": 100
   },
   {
    "filename": "golem1 6.aseprite",
    "frame": { "x": 100, "y": 0, "w": 100, "h": 100 },
    "rotated": false,
    "trimmed": false,
    "spriteSourceSize": { "x": 0, "y": 0, "w": 100, "h": 100 },
    "sourceSize": { "w": 100, "h": 100 },
    "duration": 100
   },
   {
    "filename": "golem1 7.aseprite",
    "frame": { "x": 100, "y": 100, "w": 100, "h": 100 },
    "rotated": false,
    "trimmed": false,
    "spriteSourceSize": { "x": 0, "y": 0, "w": 100, "h": 100 },
    "sourceSize": { "w": 100, "h": 100 },
    "duration": 100
   },
   {
    "filename": "golem1 8.aseprite",
    "frame": { "x": 0, "y": 0, "w": 100, "h": 100 },
    "rotated": false,
    "trimmed": false,
    "spriteSourceSize": { "x": 0, "y": 0, "w": 100, "h": 100 },
    "sourceSize": { "w": 100, "h": 100 },
    "duration": 40
   },
   {
    "filename": "golem1 9.aseprite",
    "frame": { "x": 200, "y": 100, "w": 100, "h": 100 },
    "rotated": false,
    "trimmed": false,
    "spriteSourceSize": { "x": 0, "y": 0, "w": 100, "h": 100 },
    "sourceSize": { "w": 100, "h": 100 },
    "duration": 50
   },
   {
    "filename": "golem1 10.aseprite",
    "frame": { "x": 300, "y": 100, "w": 100, "h": 100 },
    "rotated": false,
    "trimmed": false,
    "spriteSourceSize": { "x": 0, "y": 0, "w": 100, "h": 100 },
    "sourceSize": { "w": 100, "h": 100 },
    "duration": 50
   },
   {
    "filename": "golem1 11.aseprite",
    "frame": { "x": 0, "y": 200, "w": 100, "h": 100 },
    "rotated": false,
    "trimmed": false,
    "spriteSourceSize": { "x": 0, "y": 0, "w": 100, "h": 100 },
    "sourceSize": { "w": 100, "h": 100 },
    "duration": 50
   },
   {
    "filename": "golem1 12.aseprite",
    "frame": { "x": 100, "y": 200, "w": 100, "h": 100 },
    "rotated": false,
    "trimmed": false,
    "spriteSourceSize": { "x": 0, "y": 0, "w": 100, "h": 100 },
    "sourceSize": { "w": 100, "h": 100 },
    "duration": 50
   },
   {
    "filename": "golem1 13.aseprite",
    "frame": { "x": 200, "y": 200, "w": 100, "h": 100 },
    "rotated": false,
    "trimmed": false,
    "spriteSourceSize": { "x": 0, "y": 0, "w": 100, "h": 100 },
    "sourceSize": { "w": 100, "h": 100 },
    "duration": 50
   },
   {
    "filename": "golem1 14.aseprite",
    "frame": { "x": 300, "y": 200, "w": 100, "h": 100 },
    "rotated": false,
    "trimmed": false,
    "spriteSourceSize": { "x": 0, "y": 0, "w": 100, "h": 100 },
    "sourceSize": { "w": 100, "h": 100 },
    "duration": 60
   },
   {
    "filename": "golem1 15.aseprite",
    "frame": { "x": 0, "y": 300, "w": 100, "h": 100 },
    "rotated": false,
    "trimmed": false,
    "spriteSourceSize": { "x": 0, "y": 0, "w": 100, "h": 100 },
    "sourceSize": { "w": 100, "h": 100 },
    "duration": 65
   },
   {
    "filename": "golem1 16.aseprite",
    "frame": { "x": 100, "y": 300, "w": 100, "h": 100 },
    "rotated": false,
    "trimmed": false,
    "spriteSourceSize": { "x": 0, "y": 0, "w": 100, "h": 100 },
    "sourceSize": { "w": 100, "h": 100 },
    "duration": 65
   },
   {
    "filename": "golem1 17.aseprite",
    "frame": { "x": 200, "y": 300, "w": 100, "h": 100 },
    "rotated": false,
    "trimmed": false,
    "spriteSourceSize": { "x": 0, "y": 0, "w": 100, "h": 100 },
    "sourceSize": { "w": 100, "h": 100 },
    "duration": 70
   },
   {
    "filename": "golem1 18.aseprite",
    "frame": { "x": 300, "y": 300, "w": 100, "h": 100 },
    "rotated": false,
    "trimmed": false,
    "spriteSourceSize": { "x": 0, "y": 0, "w": 100, "h": 100 },
    "sourceSize": { "w": 100, "h": 100 },
    "duration": 70
   }
 ],
 "meta": {
  "app": "http://www.aseprite.org/",
  "version": "1.2.25-x64",
  "image": "golem1.png",
  "format": "RGBA8888",
  "size": { "w": 400, "h": 400 },
  "scale": "1",
  "frameTags": [
   { "name": "iddle", "from": 0, "to": 4, "direction": "forward" },
   { "name": "atack", "from": 5, "to": 6, "direction": "forward" },
   { "name": "damage", "from": 7, "to": 7, "direction": "forward" },
   { "name": "death", "from": 8, "to": 17, "direction": "forward" }
  ],
  "layers": [
   { "name": "partBack", "opacity": 255, "blendMode": "normal" },
   { "name": "partFront", "opacity": 255, "blendMode": "normal" },
   { "name": "eye", "opacity": 255, "blendMode": "normal" },
   { "name": "explosion", "opacity": 255, "blendMode": "normal" }
  ],
  "slices": [
  ]
 }
}
